LICENSE
MANIFEST.in
README.md
gptdeploy.py
requirements.txt
setup.py
gpt_dev.egg-info/PKG-INFO
gpt_dev.egg-info/SOURCES.txt
gpt_dev.egg-info/dependency_links.txt
gpt_dev.egg-info/entry_points.txt
gpt_dev.egg-info/requires.txt
gpt_dev.egg-info/top_level.txt
src/__init__.py
src/cli.py
src/constants.py
src/env.py
src/apis/__init__.py
src/apis/gpt.py
src/apis/jina_cloud.py
src/options/__init__.py
src/options/configure/__init__.py
src/options/configure/key_handling.py
src/options/deploy/__init__.py
src/options/deploy/deployer.py
src/options/generate/__init__.py
src/options/generate/generator.py
src/options/generate/templates_system.py
src/options/generate/templates_user.py
src/options/generate/static_files/__init__.py
src/options/generate/static_files/gateway/Dockerfile
src/options/generate/static_files/gateway/__init__.py
src/options/generate/static_files/gateway/app_config.toml
src/options/generate/static_files/gateway/custom_gateway.py
src/options/generate/static_files/gateway/nginx.conf
src/options/generate/static_files/gateway/requirements.txt
src/options/run/__init__.py
src/options/run/runner.py
src/utils/__init__.py
src/utils/io.py
src/utils/string_tools.py
test/__init__.py
test/test_generator.py
test/test_strings.py