Metadata-Version: 2.1
Name: gpt-dev
Version: 0.18.28.dev191
Summary: Use natural language interface to generate, deploy and update your microservice infrastructure.
Home-page: https://github.com/jina-ai/gptdeploy
Author: Florian Hönicke
Author-email: florian.hoenicke@jina.ai
License: UNKNOWN
Platform: UNKNOWN
Classifier: Development Status :: 3 - Alpha
Classifier: Intended Audience :: Developers
Classifier: License :: OSI Approved :: Apache Software License
Classifier: Programming Language :: Python :: 3
Classifier: Programming Language :: Python :: 3.8
Classifier: Programming Language :: Python :: 3.9
Classifier: Programming Language :: Python :: 3.10
Classifier: Programming Language :: Python :: 3.11
License-File: LICENSE
